np_asciiart/LICENSE
np_asciiart/README.MD
np_asciiart/__init__.py
np_asciiart/requirements.txt
np_asciiart/thirdparty.json
np_asciiart-0.10.dist-info/LICENSE.rst
np_asciiart-0.10.dist-info/METADATA
np_asciiart-0.10.dist-info/WHEEL
np_asciiart-0.10.dist-info/top_level.txt
np_asciiart-0.10.dist-info/RECORD
